openapi_generator_cli/__init__.py
openapi_generator_cli/openapi-generator.jar
python_openapi_generator_cli_jar-5.2.0.dist-info/METADATA
python_openapi_generator_cli_jar-5.2.0.dist-info/WHEEL
python_openapi_generator_cli_jar-5.2.0.dist-info/entry_points.txt
python_openapi_generator_cli_jar-5.2.0.dist-info/top_level.txt
python_openapi_generator_cli_jar-5.2.0.dist-info/RECORD
