Metadata-Version: 2.1
Name: python-openapi-generator-cli-jar
Version: 5.2.0
Summary: CLI for openapi generator
Home-page: https://github.com/OpenAPITools/openapi-generator
Author: OpenAPI Generator community
Author-email: team@openapitools.org
License: APACHE 2.0
Platform: UNKNOWN
Classifier: License :: OSI Approved :: Apache Software License
Classifier: Programming Language :: Python
Classifier: Programming Language :: Python :: Implementation :: CPython
Classifier: Programming Language :: Python :: Implementation :: PyPy
